{
  "version": "2.3.6",
  "flags": {},
  "shapes": [
    {
      "direction": 0.05273892357945442,
      "label": "kc02u",
      "points": [
        [
          280.01165771484375,
          186.81423950195312
        ],
        [
          280.97637939453125,
          168.53823852539062
        ],
        [
          189.11073303222656,
          163.6888427734375
        ],
        [
          188.14598083496094,
          181.96484375
        ]
      ],
      "group_id": null,
      "description": "",
      "difficult": false,
      "shape_type": "rotation",
      "flags": {},
      "attributes": {}
    },
    {
      "direction": 0.0766553208231926,
      "label": "kc02d",
      "points": [
        [
          395.3126525878906,
          222.44590759277344
        ],
        [
          396.7146911621094,
          204.1912384033203
        ],
        [
          310.4802551269531,
          197.5679473876953
        ],
        [
          309.0782165527344,
          215.82261657714844
        ]
      ],
      "group_id": null,
      "description": "",
      "difficult": false,
      "shape_type": "rotation",
      "flags": {},
      "attributes": {}
    },
    {
      "direction": 3.111069917678833,
      "label": "15",
      "points": [
        [
          99.40130615234375,
          298.4028015136719
        ],
        [
          99.756591796875,
          310.0394592285156
        ],
        [
          117.20539855957031,
          309.5066833496094
        ],
        [
          116.85011291503906,
          297.8700256347656
        ]
      ],
      "group_id": null,
      "description": "",
      "difficult": false,
      "shape_type": "rotation",
      "flags": {},
      "attributes": {}
    },
    {
      "direction": 0.06327062100172043,
      "label": "kc01u",
      "points": [
        [
          269.45452880859375,
          80.52566528320312
        ],
        [
          270.56793212890625,
          62.95152282714844
        ],
        [
          179.53115844726562,
          57.183868408203125
        ],
        [
          178.41775512695312,
          74.75801086425781
        ]
      ],
      "group_id": null,
      "description": "",
      "difficult": false,
      "shape_type": "rotation",
      "flags": {},
      "attributes": {}
    },
    {
      "direction": 0.07740563899278641,
      "label": "5",
      "points": [
        [
          109.64288330078125,
          25.348411560058594
        ],
        [
          110.53996276855469,
          13.782203674316406
        ],
        [
          93.27510070800781,
          12.443130493164062
        ],
        [
          92.37802124023438,
          24.00933837890625
        ]
      ],
      "group_id": null,
      "description": "",
      "difficult": false,
      "shape_type": "rotation",
      "flags": {},
      "attributes": {}
    },
    {
      "direction": 0.05138189718127251,
      "label": "9",
      "points": [
        [
          108.90731048583984,
          141.58567810058594
        ],
        [
          109.4596939086914,
          130.8446502685547
        ],
        [
          93.35750579833984,
          130.0165557861328
        ],
        [
          92.80512237548828,
          140.75758361816406
        ]
      ],
      "group_id": null,
      "description": "",
      "difficult": false,
      "shape_type": "rotation",
      "flags": {},
      "attributes": {}
    },
    {
      "direction": 3.0767087936401367,
      "label": "21",
      "points": [
        [
          103.85855102539062,
          455.7225341796875
        ],
        [
          104.56777954101562,
          466.637939453125
        ],
        [
          121.92140197753906,
          465.5103759765625
        ],
        [
          121.21217346191406,
          454.594970703125
        ]
      ],
      "group_id": null,
      "description": "",
      "difficult": false,
      "shape_type": "rotation",
      "flags": {},
      "attributes": {}
    },
    {
      "direction": 3.0104434490203857,
      "label": "27",
      "points": [
        [
          109.3268051147461,
          589.2584228515625
        ],
        [
          110.73175811767578,
          599.9095458984375
        ],
        [
          127.71715545654297,
          597.6690673828125
        ],
        [
          126.31220245361328,
          587.0179443359375
        ]
      ],
      "group_id": null,
      "description": "",
      "difficult": false,
      "shape_type": "rotation",
      "flags": {},
      "attributes": {}
    },
    {
      "direction": 3.122446060180664,
      "label": "14",
      "points": [
        [
          98.05945587158203,
          272.0943603515625
        ],
        [
          98.2837905883789,
          283.80987548828125
        ],
        [
          115.84969329833984,
          283.4735107421875
        ],
        [
          115.62535858154297,
          271.75799560546875
        ]
      ],
      "group_id": null,
      "description": "",
      "difficult": false,
      "shape_type": "rotation",
      "flags": {},
      "attributes": {}
    },
    {
      "direction": 3.0422661304473877,
      "label": "28",
      "points": [
        [
          110.9820556640625,
          609.7191162109375
        ],
        [
          112.05789184570312,
          620.5147705078125
        ],
        [
          129.44480895996094,
          618.7821044921875
        ],
        [
          128.3689727783203,
          607.9864501953125
        ]
      ],
      "group_id": null,
      "description": "",
      "difficult": false,
      "shape_type": "rotation",
      "flags": {},
      "attributes": {}
    },
    {
      "direction": 0.00033827347215265036,
      "label": "13",
      "points": [
        [
          115.50606536865234,
          256.7127685546875
        ],
        [
          115.50997161865234,
          245.18701171875
        ],
        [
          97.1764907836914,
          245.18081665039062
        ],
        [
          97.1725845336914,
          256.7065734863281
        ]
      ],
      "group_id": null,
      "description": "",
      "difficult": false,
      "shape_type": "rotation",
      "flags": {},
      "attributes": {}
    },
    {
      "direction": 3.0657293796539307,
      "label": "20",
      "points": [
        [
          101.8788070678711,
          423.0748291015625
        ],
        [
          102.71448516845703,
          434.06927490234375
        ],
        [
          120.56185150146484,
          432.71270751953125
        ],
        [
          119.7261734008789,
          421.71826171875
        ]
      ],
      "group_id": null,
      "description": "",
      "difficult": false,
      "shape_type": "rotation",
      "flags": {},
      "attributes": {}
    },
    {
      "direction": 3.0675771236419678,
      "label": "22",
      "points": [
        [
          104.39390563964844,
          479.0426330566406
        ],
        [
          105.1724853515625,
          489.5425720214844
        ],
        [
          122.78364562988281,
          488.2366638183594
        ],
        [
          122.00506591796875,
          477.7367248535156
        ]
      ],
      "group_id": null,
      "description": "",
      "difficult": false,
      "shape_type": "rotation",
      "flags": {},
      "attributes": {}
    },
    {
      "direction": 0.05928736552596092,
      "label": "kc03d",
      "points": [
        [
          269.5303039550781,
          30.912765502929688
        ],
        [
          270.6298522949219,
          12.38883113861084
        ],
        [
          180.2188720703125,
          7.02231502532959
        ],
        [
          179.11935424804688,
          25.546249389648438
        ]
      ],
      "group_id": null,
      "description": "",
      "difficult": false,
      "shape_type": "rotation",
      "flags": {},
      "attributes": {}
    },
    {
      "direction": 3.0784332752227783,
      "label": "23",
      "points": [
        [
          105.4460678100586,
          502.0138244628906
        ],
        [
          106.1290054321289,
          512.8123168945312
        ],
        [
          123.86177825927734,
          511.6908264160156
        ],
        [
          123.17884063720703,
          500.8923645019531
        ]
      ],
      "group_id": null,
      "description": "",
      "difficult": false,
      "shape_type": "rotation",
      "flags": {},
      "attributes": {}
    },
    {
      "direction": 3.0905802249908447,
      "label": "16",
      "points": [
        [
          99.97966003417969,
          324.1972351074219
        ],
        [
          100.56808471679688,
          335.7221984863281
        ],
        [
          117.74842834472656,
          334.8450012207031
        ],
        [
          117.16000366210938,
          323.3200378417969
        ]
      ],
      "group_id": null,
      "description": "",
      "difficult": false,
      "shape_type": "rotation",
      "flags": {},
      "attributes": {}
    },
    {
      "direction": 3.0581860542297363,
      "label": "24",
      "points": [
        [
          105.7635726928711,
          524.7123413085938
        ],
        [
          106.71773529052734,
          536.1256713867188
        ],
        [
          124.84542083740234,
          534.6101684570312
        ],
        [
          123.8912582397461,
          523.1968383789062
        ]
      ],
      "group_id": null,
      "description": "",
      "difficult": false,
      "shape_type": "rotation",
      "flags": {},
      "attributes": {}
    },
    {
      "direction": 3.0950582027435303,
      "label": "17",
      "points": [
        [
          100.0284652709961,
          349.0269470214844
        ],
        [
          100.56900787353516,
          360.6346740722656
        ],
        [
          117.86458587646484,
          359.8292541503906
        ],
        [
          117.32404327392578,
          348.2215270996094
        ]
      ],
      "group_id": null,
      "description": "",
      "difficult": false,
      "shape_type": "rotation",
      "flags": {},
      "attributes": {}
    },
    {
      "direction": 0.0004100851947441697,
      "label": "krad",
      "points": [
        [
          258.0480651855469,
          354.2226257324219
        ],
        [
          258.0542907714844,
          339.0116882324219
        ],
        [
          179.607666015625,
          338.9795227050781
        ],
        [
          179.6014404296875,
          354.1904602050781
        ]
      ],
      "group_id": null,
      "description": "",
      "difficult": false,
      "shape_type": "rotation",
      "flags": {},
      "attributes": {}
    },
    {
      "direction": 3.070061445236206,
      "label": "19",
      "points": [
        [
          101.91685485839844,
          399.0468444824219
        ],
        [
          102.69161987304688,
          409.8595275878906
        ],
        [
          119.64790344238281,
          408.6445617675781
        ],
        [
          118.87313842773438,
          397.8318786621094
        ]
      ],
      "group_id": null,
      "description": "",
      "difficult": false,
      "shape_type": "rotation",
      "flags": {},
      "attributes": {}
    },
    {
      "direction": 3.056870460510254,
      "label": "25",
      "points": [
        [
          107.34748840332031,
          546.221435546875
        ],
        [
          108.27983093261719,
          557.1998291015625
        ],
        [
          126.12506103515625,
          555.684326171875
        ],
        [
          125.19271850585938,
          544.7059326171875
        ]
      ],
      "group_id": null,
      "description": "",
      "difficult": false,
      "shape_type": "rotation",
      "flags": {},
      "attributes": {}
    },
    {
      "direction": 0.05163515731692314,
      "label": "8",
      "points": [
        [
          108.78862762451172,
          112.68045806884766
        ],
        [
          109.35819244384766,
          101.6596450805664
        ],
        [
          92.99857330322266,
          100.81415557861328
        ],
        [
          92.42900848388672,
          111.83496856689453
        ]
      ],
      "group_id": null,
      "description": "",
      "difficult": false,
      "shape_type": "rotation",
      "flags": {},
      "attributes": {}
    },
    {
      "direction": 0.026002679020166397,
      "label": "12",
      "points": [
        [
          114.14500427246094,
          230.30206298828125
        ],
        [
          114.45970153808594,
          218.20245361328125
        ],
        [
          95.83985900878906,
          217.71817016601562
        ],
        [
          95.52516174316406,
          229.81777954101562
        ]
      ],
      "group_id": null,
      "description": "",
      "difficult": false,
      "shape_type": "rotation",
      "flags": {},
      "attributes": {}
    },
    {
      "direction": 0.06067819148302078,
      "label": "kd1",
      "points": [
        [
          481.8619689941406,
          223.42367553710938
        ],
        [
          482.8652038574219,
          206.91012573242188
        ],
        [
          434.8142395019531,
          203.99090576171875
        ],
        [
          433.8110046386719,
          220.50445556640625
        ]
      ],
      "group_id": null,
      "description": "",
      "difficult": false,
      "shape_type": "rotation",
      "flags": {},
      "attributes": {}
    },
    {
      "direction": 0.0611896738409996,
      "label": "6",
      "points": [
        [
          109.57501220703125,
          55.06607437133789
        ],
        [
          110.29978942871094,
          43.23611831665039
        ],
        [
          93.08576965332031,
          42.18148422241211
        ],
        [
          92.36099243164062,
          54.01144027709961
        ]
      ],
      "group_id": null,
      "description": "",
      "difficult": false,
      "shape_type": "rotation",
      "flags": {},
      "attributes": {}
    },
    {
      "direction": 3.100576877593994,
      "label": "18",
      "points": [
        [
          101.10472106933594,
          374.2569580078125
        ],
        [
          101.55496215820312,
          385.22821044921875
        ],
        [
          118.79194641113281,
          384.52081298828125
        ],
        [
          118.34170532226562,
          373.549560546875
        ]
      ],
      "group_id": null,
      "description": "",
      "difficult": false,
      "shape_type": "rotation",
      "flags": {},
      "attributes": {}
    },
    {
      "direction": 0.058035578578710556,
      "label": "7",
      "points": [
        [
          109.11776733398438,
          83.8024673461914
        ],
        [
          109.80165100097656,
          72.0317611694336
        ],
        [
          93.443603515625,
          71.08135223388672
        ],
        [
          92.75971984863281,
          82.85205841064453
        ]
      ],
      "group_id": null,
      "description": "",
      "difficult": false,
      "shape_type": "rotation",
      "flags": {},
      "attributes": {}
    },
    {
      "direction": 0.1034710481762886,
      "label": "kd2",
      "points": [
        [
          606.1336059570312,
          231.17990112304688
        ],
        [
          607.8587036132812,
          214.56723022460938
        ],
        [
          556.2734985351562,
          209.21051025390625
        ],
        [
          554.5484008789062,
          225.82318115234375
        ]
      ],
      "group_id": null,
      "description": "",
      "difficult": false,
      "shape_type": "rotation",
      "flags": {},
      "attributes": {}
    },
    {
      "direction": 3.0436034202575684,
      "label": "26",
      "points": [
        [
          108.12390899658203,
          568.0743408203125
        ],
        [
          109.17028045654297,
          578.7186279296875
        ],
        [
          127.5399398803711,
          576.912841796875
        ],
        [
          126.49356842041016,
          566.2685546875
        ]
      ],
      "group_id": null,
      "description": "",
      "difficult": false,
      "shape_type": "rotation",
      "flags": {},
      "attributes": {}
    },
    {
      "direction": 0.04393482580780983,
      "label": "11",
      "points": [
        [
          113.00021362304688,
          202.43531799316406
        ],
        [
          113.50576782226562,
          190.93592834472656
        ],
        [
          95.71583557128906,
          190.15382385253906
        ],
        [
          95.21028137207031,
          201.65321350097656
        ]
      ],
      "group_id": null,
      "description": "",
      "difficult": false,
      "shape_type": "rotation",
      "flags": {},
      "attributes": {}
    },
    {
      "direction": 0.04176240414381027,
      "label": "10",
      "points": [
        [
          111.72692108154297,
          170.98687744140625
        ],
        [
          112.20732879638672,
          159.49026489257812
        ],
        [
          93.2359848022461,
          158.697509765625
        ],
        [
          92.75557708740234,
          170.19412231445312
        ]
      ],
      "group_id": null,
      "description": "",
      "difficult": false,
      "shape_type": "rotation",
      "flags": {},
      "attributes": {}
    },
    {
      "direction": 0.06396673619747162,
      "label": "kc01d",
      "points": [
        [
          263.6817626953125,
          211.949951171875
        ],
        [
          264.74554443359375,
          195.34210205078125
        ],
        [
          174.33164978027344,
          189.55072021484375
        ],
        [
          173.26783752441406,
          206.1585693359375
        ]
      ],
      "group_id": null,
      "description": "",
      "difficult": false,
      "shape_type": "rotation",
      "flags": {},
      "attributes": {}
    },
    {
      "direction": 3.06072998046875,
      "label": "29",
      "points": [
        [
          111.7412109375,
          629.781494140625
        ],
        [
          112.59989929199219,
          640.37744140625
        ],
        [
          130.3487548828125,
          638.9390869140625
        ],
        [
          129.49005126953125,
          628.3431396484375
        ]
      ],
      "group_id": null,
      "description": "",
      "difficult": false,
      "shape_type": "rotation",
      "flags": {},
      "attributes": {}
    },
    {
      "direction": 3.1283681392669678,
      "label": "krau",
      "points": [
        [
          180.83839416503906,
          386.7715759277344
        ],
        [
          181.03648376464844,
          401.7495422363281
        ],
        [
          255.1387481689453,
          400.7695007324219
        ],
        [
          254.94065856933594,
          385.7915344238281
        ]
      ],
      "group_id": null,
      "description": "",
      "difficult": false,
      "shape_type": "rotation",
      "flags": {},
      "attributes": {}
    },
    {
      "direction": 0.0038572351913899183,
      "label": "krbu",
      "points": [
        [
          247.51231384277344,
          423.97723388671875
        ],
        [
          247.5666961669922,
          409.8790283203125
        ],
        [
          181.12242126464844,
          409.62274169921875
        ],
        [
          181.0680389404297,
          423.720947265625
        ]
      ],
      "group_id": null,
      "description": "",
      "difficult": false,
      "shape_type": "rotation",
      "flags": {},
      "attributes": {}
    },
    {
      "direction": 0.018769824877381325,
      "label": "krbd",
      "points": [
        [
          370.8717956542969,
          356.06231689453125
        ],
        [
          371.1643981933594,
          340.47491455078125
        ],
        [
          301.6056213378906,
          339.16912841796875
        ],
        [
          301.3130187988281,
          354.75653076171875
        ]
      ],
      "group_id": null,
      "description": "",
      "difficult": false,
      "shape_type": "rotation",
      "flags": {},
      "attributes": {}
    }
  ],
  "imagePath": "IMG_20251106_110552.jpg",
  "imageData": null,
  "imageHeight": 640,
  "imageWidth": 640,
  "text": ""
}