{
  "version": "2.3.6",
  "flags": {},
  "shapes": [
    {
      "direction": 3.0851540565490723,
      "label": "18",
      "points": [
        [
          96.0017318725586,
          144.37918090820312
        ],
        [
          96.71382904052734,
          156.98287963867188
        ],
        [
          115.13541412353516,
          155.94207763671875
        ],
        [
          114.4233169555664,
          143.33837890625
        ]
      ],
      "group_id": null,
      "description": "",
      "difficult": false,
      "shape_type": "rotation",
      "flags": {},
      "attributes": {}
    },
    {
      "direction": 0.18363428115844727,
      "label": "31",
      "points": [
        [
          142.00265502929688,
          507.92169189453125
        ],
        [
          143.90362548828125,
          497.6864013671875
        ],
        [
          126.77945709228516,
          494.5059814453125
        ],
        [
          124.87848663330078,
          504.74127197265625
        ]
      ],
      "group_id": null,
      "description": "",
      "difficult": false,
      "shape_type": "rotation",
      "flags": {},
      "attributes": {}
    },
    {
      "direction": 0.161596417427063,
      "label": "30",
      "points": [
        [
          143.89913940429688,
          481.61297607421875
        ],
        [
          145.64288330078125,
          470.9163818359375
        ],
        [
          128.24427795410156,
          468.080078125
        ],
        [
          126.50054931640625,
          478.77667236328125
        ]
      ],
      "group_id": null,
      "description": "",
      "difficult": false,
      "shape_type": "rotation",
      "flags": {},
      "attributes": {}
    },
    {
      "direction": 3.0602121353149414,
      "label": "krcu",
      "points": [
        [
          464.03618720026304,
          75.49007317571356
        ],
        [
          466.40081122370054,
          104.48238274602606
        ],
        [
          583.7030573174505,
          94.91513726262762
        ],
        [
          581.338433294013,
          65.92282769231512
        ]
      ],
      "group_id": null,
      "description": "",
      "difficult": false,
      "shape_type": "rotation",
      "flags": {},
      "attributes": {}
    },
    {
      "direction": 0.10670454800128937,
      "label": "29",
      "points": [
        [
          142.69728088378906,
          457.2518615722656
        ],
        [
          143.8267059326172,
          446.7076110839844
        ],
        [
          126.04352569580078,
          444.8028259277344
        ],
        [
          124.91411590576172,
          455.3470764160156
        ]
      ],
      "group_id": null,
      "description": "",
      "difficult": false,
      "shape_type": "rotation",
      "flags": {},
      "attributes": {}
    },
    {
      "direction": 0.24992657423019415,
      "label": "kc11",
      "points": [
        [
          267.2006459719321,
          394.74421785924557
        ],
        [
          271.45788940212043,
          378.06638415808317
        ],
        [
          223.91890664037268,
          365.9313802852857
        ],
        [
          219.66166321018426,
          382.6092139864481
        ]
      ],
      "group_id": null,
      "description": "",
      "difficult": false,
      "shape_type": "rotation",
      "flags": {},
      "attributes": {}
    },
    {
      "direction": 3.055647850036621,
      "label": "15",
      "points": [
        [
          88.47991943359375,
          50.61079406738281
        ],
        [
          89.57341003417969,
          63.30254364013672
        ],
        [
          107.21614074707031,
          61.782501220703125
        ],
        [
          106.12265014648438,
          49.09075164794922
        ]
      ],
      "group_id": null,
      "description": "",
      "difficult": false,
      "shape_type": "rotation",
      "flags": {},
      "attributes": {}
    },
    {
      "direction": 0.36025020480155945,
      "label": "krbd",
      "points": [
        [
          271.6832275390625,
          496.3431091308594
        ],
        [
          278.36090087890625,
          478.6157531738281
        ],
        [
          226.2959747314453,
          459.0035095214844
        ],
        [
          219.61827087402344,
          476.7308654785156
        ]
      ],
      "group_id": null,
      "description": "",
      "difficult": false,
      "shape_type": "rotation",
      "flags": {},
      "attributes": {}
    },
    {
      "direction": 0.19901397824287415,
      "label": "32",
      "points": [
        [
          143.36105346679688,
          529.978271484375
        ],
        [
          145.25802612304688,
          520.5726318359375
        ],
        [
          128.21517944335938,
          517.1353759765625
        ],
        [
          126.31820678710938,
          526.541015625
        ]
      ],
      "group_id": null,
      "description": "",
      "difficult": false,
      "shape_type": "rotation",
      "flags": {},
      "attributes": {}
    },
    {
      "direction": 0.09635335952043533,
      "label": "26",
      "points": [
        [
          135.82901000976562,
          383.3785095214844
        ],
        [
          136.87045288085938,
          372.6034851074219
        ],
        [
          119.62737274169922,
          370.9369201660156
        ],
        [
          118.58594512939453,
          381.7119445800781
        ]
      ],
      "group_id": null,
      "description": "",
      "difficult": false,
      "shape_type": "rotation",
      "flags": {},
      "attributes": {}
    },
    {
      "direction": 0.04504598677158356,
      "label": "23",
      "points": [
        [
          129.25282287597656,
          304.7085266113281
        ],
        [
          129.7551727294922,
          293.5638732910156
        ],
        [
          111.96408081054688,
          292.7619323730469
        ],
        [
          111.46171569824219,
          303.9065856933594
        ]
      ],
      "group_id": null,
      "description": "",
      "difficult": false,
      "shape_type": "rotation",
      "flags": {},
      "attributes": {}
    },
    {
      "direction": 3.1049740314483643,
      "label": "17",
      "points": [
        [
          93.83382415771484,
          112.78713989257812
        ],
        [
          94.30960845947266,
          125.7744140625
        ],
        [
          112.59412384033203,
          125.10455322265625
        ],
        [
          112.11833953857422,
          112.11727905273438
        ]
      ],
      "group_id": null,
      "description": "",
      "difficult": false,
      "shape_type": "rotation",
      "flags": {},
      "attributes": {}
    },
    {
      "direction": 0.019589340314269066,
      "label": "22",
      "points": [
        [
          126.62734985351562,
          277.3459167480469
        ],
        [
          126.84895324707031,
          266.0346374511719
        ],
        [
          109.54920959472656,
          265.6957092285156
        ],
        [
          109.32760620117188,
          277.0069885253906
        ]
      ],
      "group_id": null,
      "description": "",
      "difficult": false,
      "shape_type": "rotation",
      "flags": {},
      "attributes": {}
    },
    {
      "direction": 0.09754756838083267,
      "label": "28",
      "points": [
        [
          140.26800537109375,
          433.4023132324219
        ],
        [
          141.330322265625,
          422.5466003417969
        ],
        [
          123.98279571533203,
          420.8490295410156
        ],
        [
          122.92047882080078,
          431.7047424316406
        ]
      ],
      "group_id": null,
      "description": "",
      "difficult": false,
      "shape_type": "rotation",
      "flags": {},
      "attributes": {}
    },
    {
      "direction": 0.10269235819578171,
      "label": "27",
      "points": [
        [
          137.69993591308594,
          408.52197265625
        ],
        [
          138.8341827392578,
          397.5157470703125
        ],
        [
          121.99635314941406,
          395.780517578125
        ],
        [
          120.86210632324219,
          406.7867431640625
        ]
      ],
      "group_id": null,
      "description": "",
      "difficult": false,
      "shape_type": "rotation",
      "flags": {},
      "attributes": {}
    },
    {
      "direction": 3.101059913635254,
      "label": "19",
      "points": [
        [
          98.12944030761719,
          174.51380920410156
        ],
        [
          98.63117980957031,
          186.88572692871094
        ],
        [
          117.29011535644531,
          186.12901306152344
        ],
        [
          116.78837585449219,
          173.75709533691406
        ]
      ],
      "group_id": null,
      "description": "",
      "difficult": false,
      "shape_type": "rotation",
      "flags": {},
      "attributes": {}
    },
    {
      "direction": 3.133122205734253,
      "label": "20",
      "points": [
        [
          100.93704223632812,
          203.43165588378906
        ],
        [
          101.04393005371094,
          216.04945373535156
        ],
        [
          119.62576293945312,
          215.8920440673828
        ],
        [
          119.51887512207031,
          203.2742462158203
        ]
      ],
      "group_id": null,
      "description": "",
      "difficult": false,
      "shape_type": "rotation",
      "flags": {},
      "attributes": {}
    },
    {
      "direction": 0.07921554148197174,
      "label": "24",
      "points": [
        [
          131.527587890625,
          332.2204284667969
        ],
        [
          132.42501831054688,
          320.9151306152344
        ],
        [
          114.52762603759766,
          319.4944152832031
        ],
        [
          113.63019561767578,
          330.7997131347656
        ]
      ],
      "group_id": null,
      "description": "",
      "difficult": false,
      "shape_type": "rotation",
      "flags": {},
      "attributes": {}
    },
    {
      "direction": 0.017615405842661858,
      "label": "21",
      "points": [
        [
          123.68832397460938,
          250.30575561523438
        ],
        [
          123.89813232421875,
          238.39617919921875
        ],
        [
          105.2918701171875,
          238.06838989257812
        ],
        [
          105.08206176757812,
          249.97796630859375
        ]
      ],
      "group_id": null,
      "description": "",
      "difficult": false,
      "shape_type": "rotation",
      "flags": {},
      "attributes": {}
    },
    {
      "direction": 0.08118423074483871,
      "label": "25",
      "points": [
        [
          134.0840301513672,
          358.1576843261719
        ],
        [
          135.0085906982422,
          346.7942810058594
        ],
        [
          117.55018615722656,
          345.3738098144531
        ],
        [
          116.62562561035156,
          356.7372131347656
        ]
      ],
      "group_id": null,
      "description": "",
      "difficult": false,
      "shape_type": "rotation",
      "flags": {},
      "attributes": {}
    },
    {
      "direction": 3.0553746223449707,
      "label": "krcd",
      "points": [
        [
          312.9795227050781,
          95.00017547607422
        ],
        [
          315.1418762207031,
          120.0182876586914
        ],
        [
          400.4474792480469,
          112.64513397216797
        ],
        [
          398.2851257324219,
          87.62702178955078
        ]
      ],
      "group_id": null,
      "description": "",
      "difficult": false,
      "shape_type": "rotation",
      "flags": {},
      "attributes": {}
    },
    {
      "direction": 3.0765247344970703,
      "label": "16",
      "points": [
        [
          91.2462158203125,
          81.94725036621094
        ],
        [
          92.08087158203125,
          94.75662231445312
        ],
        [
          110.91815185546875,
          93.52919006347656
        ],
        [
          110.08349609375,
          80.71981811523438
        ]
      ],
      "group_id": null,
      "description": "",
      "difficult": false,
      "shape_type": "rotation",
      "flags": {},
      "attributes": {}
    },
    {
      "direction": 3.051501512527466,
      "label": "14",
      "points": [
        [
          86.36114501953125,
          18.809062957763672
        ],
        [
          87.57083129882812,
          32.20005798339844
        ],
        [
          105.64741516113281,
          30.567096710205078
        ],
        [
          104.43772888183594,
          17.176101684570312
        ]
      ],
      "group_id": null,
      "description": "",
      "difficult": false,
      "shape_type": "rotation",
      "flags": {},
      "attributes": {}
    },
    {
      "direction": 3.1015443801879883,
      "label": "yf",
      "points": [
        [
          203.26202392578125,
          109.21553802490234
        ],
        [
          203.99737548828125,
          127.56739044189453
        ],
        [
          230.33096313476562,
          126.51221466064453
        ],
        [
          229.59561157226562,
          108.16036224365234
        ]
      ],
      "group_id": null,
      "description": "",
      "difficult": false,
      "shape_type": "rotation",
      "flags": {},
      "attributes": {}
    },
    {
      "direction": 0.10605712443590164,
      "label": "kc05d",
      "points": [
        [
          279.21717205001914,
          284.31690852272476
        ],
        [
          281.1376545513085,
          266.2769834998618
        ],
        [
          213.78757343337926,
          259.107102707744
        ],
        [
          211.86712144814217,
          277.1470280357776
        ]
      ],
      "group_id": null,
      "description": "",
      "difficult": false,
      "shape_type": "rotation",
      "flags": {},
      "attributes": {}
    },
    {
      "direction": 0.13431013256311417,
      "label": "kc06d",
      "points": [
        [
          218.10903582604885,
          286.5931093536908
        ],
        [
          292.3288662049327,
          296.6219614535975
        ],
        [
          289.6301604212917,
          316.5940862300918
        ],
        [
          215.4103300424079,
          306.5652341301851
        ]
      ],
      "group_id": null,
      "description": "",
      "difficult": false,
      "shape_type": "rotation",
      "flags": {},
      "attributes": {}
    },
    {
      "direction": 0.002196577377617359,
      "label": "cdyb",
      "points": [
        [
          405.2559509277344,
          197.97763061523438
        ],
        [
          405.3088684082031,
          173.8941650390625
        ],
        [
          324.1435241699219,
          173.71588134765625
        ],
        [
          324.0906066894531,
          197.79934692382812
        ]
      ],
      "group_id": null,
      "description": "",
      "difficult": false,
      "shape_type": "rotation",
      "flags": {},
      "attributes": {}
    },
    {
      "direction": 0.2403140980005265,
      "label": "kc10",
      "points": [
        [
          269.18238968722454,
          368.6860942424039
        ],
        [
          273.1885604078256,
          352.33780963155135
        ],
        [
          220.55068635170267,
          339.4388924628097
        ],
        [
          216.54454605107563,
          355.7871795124651
        ]
      ],
      "group_id": null,
      "description": "",
      "difficult": false,
      "shape_type": "rotation",
      "flags": {},
      "attributes": {}
    },
    {
      "direction": 0.04311289612203837,
      "label": "kc13",
      "points": [
        [
          256.7506206585314,
          225.55333831619762
        ],
        [
          257.5798080975303,
          206.33192083817093
        ],
        [
          207.76162625707826,
          204.1827934085471
        ],
        [
          206.93240831423304,
          223.4042099711838
        ]
      ],
      "group_id": null,
      "description": "",
      "difficult": false,
      "shape_type": "rotation",
      "flags": {},
      "attributes": {}
    },
    {
      "direction": 0.02314920365810334,
      "label": "kc04d",
      "points": [
        [
          211.2827422291672,
          170.40266211483222
        ],
        [
          283.7380706540597,
          172.08024494353813
        ],
        [
          283.15072029417666,
          197.44809116704636
        ],
        [
          210.6953918692841,
          195.77050833834045
        ]
      ],
      "group_id": null,
      "description": "",
      "difficult": false,
      "shape_type": "rotation",
      "flags": {},
      "attributes": {}
    },
    {
      "direction": 0.18997619926929477,
      "label": "kc09",
      "points": [
        [
          261.0601303596736,
          340.0896930673233
        ],
        [
          264.26946533963184,
          323.4000064968553
        ],
        [
          214.46010279462328,
          313.8219280264267
        ],
        [
          211.25076781466504,
          330.5116145968947
        ]
      ],
      "group_id": null,
      "description": "",
      "difficult": false,
      "shape_type": "rotation",
      "flags": {},
      "attributes": {}
    }
  ],
  "imagePath": "IMG_20251106_103857.jpg",
  "imageData": null,
  "imageHeight": 640,
  "imageWidth": 640,
  "text": ""
}