{
  "version": "2.3.6",
  "flags": {},
  "shapes": [
    {
      "direction": 0.10608557611703873,
      "label": "20",
      "points": [
        [
          115.49820709228516,
          532.842529296875
        ],
        [
          116.5790023803711,
          522.69287109375
        ],
        [
          99.73612213134766,
          520.8992919921875
        ],
        [
          98.65532684326172,
          531.0489501953125
        ]
      ],
      "group_id": null,
      "description": "",
      "difficult": false,
      "shape_type": "rotation",
      "flags": {},
      "attributes": {}
    },
    {
      "direction": 0.00039510492933914065,
      "label": "iu",
      "points": [
        [
          221.13451911954422,
          101.96430693341358
        ],
        [
          221.14150764493485,
          84.29000578595262
        ],
        [
          189.76284553555985,
          84.2776003904448
        ],
        [
          189.75585701016922,
          101.95190153790577
        ]
      ],
      "group_id": null,
      "description": "",
      "difficult": false,
      "shape_type": "rotation",
      "flags": {},
      "attributes": {}
    },
    {
      "direction": 0.009624175727367401,
      "label": "4",
      "points": [
        [
          89.32006072998047,
          131.9879913330078
        ],
        [
          89.43811798095703,
          119.72112274169922
        ],
        [
          71.42913055419922,
          119.54779815673828
        ],
        [
          71.31107330322266,
          131.81466674804688
        ]
      ],
      "group_id": null,
      "description": "",
      "difficult": false,
      "shape_type": "rotation",
      "flags": {},
      "attributes": {}
    },
    {
      "direction": 0.062557652592659,
      "label": "14",
      "points": [
        [
          108.15128326416016,
          404.0802001953125
        ],
        [
          108.8161392211914,
          393.46612548828125
        ],
        [
          92.84647369384766,
          392.4658203125
        ],
        [
          92.1816177368164,
          403.07989501953125
        ]
      ],
      "group_id": null,
      "description": "",
      "difficult": false,
      "shape_type": "rotation",
      "flags": {},
      "attributes": {}
    },
    {
      "direction": 0.08039121329784393,
      "label": "19",
      "points": [
        [
          114.1217269897461,
          512.54931640625
        ],
        [
          114.9121322631836,
          502.7384338378906
        ],
        [
          98.97803497314453,
          501.4546813964844
        ],
        [
          98.18762969970703,
          511.2655334472656
        ]
      ],
      "group_id": null,
      "description": "",
      "difficult": false,
      "shape_type": "rotation",
      "flags": {},
      "attributes": {}
    },
    {
      "direction": 0.11050467193126678,
      "label": "21",
      "points": [
        [
          117.90330505371094,
          554.992431640625
        ],
        [
          118.92245483398438,
          545.807373046875
        ],
        [
          102.57061767578125,
          543.9930419921875
        ],
        [
          101.55146789550781,
          553.1781005859375
        ]
      ],
      "group_id": null,
      "description": "",
      "difficult": false,
      "shape_type": "rotation",
      "flags": {},
      "attributes": {}
    },
    {
      "direction": 0.0646619200706482,
      "label": "13",
      "points": [
        [
          106.0586166381836,
          379.3893737792969
        ],
        [
          106.78787994384766,
          368.1270446777344
        ],
        [
          89.41703033447266,
          367.0022277832031
        ],
        [
          88.6877670288086,
          378.2645568847656
        ]
      ],
      "group_id": null,
      "description": "",
      "difficult": false,
      "shape_type": "rotation",
      "flags": {},
      "attributes": {}
    },
    {
      "direction": 0.08306781202554703,
      "label": "18",
      "points": [
        [
          113.02320098876953,
          492.0695495605469
        ],
        [
          113.83074188232422,
          482.3704528808594
        ],
        [
          98.06449127197266,
          481.0577697753906
        ],
        [
          97.25695037841797,
          490.7568664550781
        ]
      ],
      "group_id": null,
      "description": "",
      "difficult": false,
      "shape_type": "rotation",
      "flags": {},
      "attributes": {}
    },
    {
      "direction": 0.07271840423345566,
      "label": "17",
      "points": [
        [
          111.594970703125,
          471.1391296386719
        ],
        [
          112.36276245117188,
          460.5993957519531
        ],
        [
          96.80169677734375,
          459.4658508300781
        ],
        [
          96.03390502929688,
          470.0055847167969
        ]
      ],
      "group_id": null,
      "description": "",
      "difficult": false,
      "shape_type": "rotation",
      "flags": {},
      "attributes": {}
    },
    {
      "direction": 0.06288310140371323,
      "label": "15",
      "points": [
        [
          110.79338073730469,
          427.1139831542969
        ],
        [
          111.4615478515625,
          416.5023498535156
        ],
        [
          94.79560852050781,
          415.4529724121094
        ],
        [
          94.12744140625,
          426.0646057128906
        ]
      ],
      "group_id": null,
      "description": "",
      "difficult": false,
      "shape_type": "rotation",
      "flags": {},
      "attributes": {}
    },
    {
      "direction": 0.023301640525460243,
      "label": "6",
      "points": [
        [
          92.31376647949219,
          191.62330627441406
        ],
        [
          92.58442687988281,
          180.00978088378906
        ],
        [
          75.66783142089844,
          179.6155242919922
        ],
        [
          75.39717102050781,
          191.2290496826172
        ]
      ],
      "group_id": null,
      "description": "",
      "difficult": false,
      "shape_type": "rotation",
      "flags": {},
      "attributes": {}
    },
    {
      "direction": 0.07671533524990082,
      "label": "16",
      "points": [
        [
          111.5661392211914,
          449.3082275390625
        ],
        [
          112.35774993896484,
          439.00958251953125
        ],
        [
          95.8196792602539,
          437.73834228515625
        ],
        [
          95.02806854248047,
          448.0369873046875
        ]
      ],
      "group_id": null,
      "description": "",
      "difficult": false,
      "shape_type": "rotation",
      "flags": {},
      "attributes": {}
    },
    {
      "direction": 3.107743501663208,
      "label": "2",
      "points": [
        [
          66.67964935302734,
          56.75156021118164
        ],
        [
          67.10478973388672,
          69.30653381347656
        ],
        [
          84.96442413330078,
          68.70176696777344
        ],
        [
          84.5392837524414,
          56.146793365478516
        ]
      ],
      "group_id": null,
      "description": "",
      "difficult": false,
      "shape_type": "rotation",
      "flags": {},
      "attributes": {}
    },
    {
      "direction": 0.035301219671964645,
      "label": "7",
      "points": [
        [
          94.32758331298828,
          220.08860778808594
        ],
        [
          94.74071502685547,
          208.39039611816406
        ],
        [
          78.33260345458984,
          207.81092834472656
        ],
        [
          77.91947174072266,
          219.50914001464844
        ]
      ],
      "group_id": null,
      "description": "",
      "difficult": false,
      "shape_type": "rotation",
      "flags": {},
      "attributes": {}
    },
    {
      "direction": 3.109184503555298,
      "label": "1",
      "points": [
        [
          64.62979125976562,
          23.77465057373047
        ],
        [
          65.05230712890625,
          36.80755615234375
        ],
        [
          82.87672424316406,
          36.229698181152344
        ],
        [
          82.45420837402344,
          23.196792602539062
        ]
      ],
      "group_id": null,
      "description": "",
      "difficult": false,
      "shape_type": "rotation",
      "flags": {},
      "attributes": {}
    },
    {
      "direction": 0.009321761317551136,
      "label": "5",
      "points": [
        [
          91.42918395996094,
          161.92181396484375
        ],
        [
          91.53886413574219,
          150.15536499023438
        ],
        [
          73.74894714355469,
          149.98953247070312
        ],
        [
          73.63926696777344,
          161.7559814453125
        ]
      ],
      "group_id": null,
      "description": "",
      "difficult": false,
      "shape_type": "rotation",
      "flags": {},
      "attributes": {}
    },
    {
      "direction": 0.050997842103242874,
      "label": "12",
      "points": [
        [
          104.78673553466797,
          354.8748474121094
        ],
        [
          105.3661880493164,
          343.5224304199219
        ],
        [
          88.28597259521484,
          342.6506042480469
        ],
        [
          87.7065200805664,
          354.0030212402344
        ]
      ],
      "group_id": null,
      "description": "",
      "difficult": false,
      "shape_type": "rotation",
      "flags": {},
      "attributes": {}
    },
    {
      "direction": 0.03442506119608879,
      "label": "8",
      "points": [
        [
          96.97470092773438,
          247.91793823242188
        ],
        [
          97.36610412597656,
          236.55282592773438
        ],
        [
          80.00221252441406,
          235.954833984375
        ],
        [
          79.61080932617188,
          247.3199462890625
        ]
      ],
      "group_id": null,
      "description": "",
      "difficult": false,
      "shape_type": "rotation",
      "flags": {},
      "attributes": {}
    },
    {
      "direction": 0.0788012444972992,
      "label": "ib'",
      "points": [
        [
          210.8275604248047,
          279.5533447265625
        ],
        [
          212.2307586669922,
          261.7835693359375
        ],
        [
          183.9337615966797,
          259.54913330078125
        ],
        [
          182.5305633544922,
          277.31890869140625
        ]
      ],
      "group_id": null,
      "description": "",
      "difficult": false,
      "shape_type": "rotation",
      "flags": {},
      "attributes": {}
    },
    {
      "direction": 3.112696886062622,
      "label": "3",
      "points": [
        [
          68.90227508544922,
          88.38471221923828
        ],
        [
          69.26012420654297,
          100.76517486572266
        ],
        [
          86.84113311767578,
          100.25701141357422
        ],
        [
          86.48328399658203,
          87.87654876708984
        ]
      ],
      "group_id": null,
      "description": "",
      "difficult": false,
      "shape_type": "rotation",
      "flags": {},
      "attributes": {}
    },
    {
      "direction": 0.11709805577993393,
      "label": "24",
      "points": [
        [
          120.38845825195312,
          609.7418212890625
        ],
        [
          121.46012878417969,
          600.6317138671875
        ],
        [
          105.65386962890625,
          598.7723388671875
        ],
        [
          104.58219909667969,
          607.8824462890625
        ]
      ],
      "group_id": null,
      "description": "",
      "difficult": false,
      "shape_type": "rotation",
      "flags": {},
      "attributes": {}
    },
    {
      "direction": 0.1213662177324295,
      "label": "22",
      "points": [
        [
          118.45272827148438,
          573.711181640625
        ],
        [
          119.55732727050781,
          564.654541015625
        ],
        [
          103.79972839355469,
          562.732666015625
        ],
        [
          102.69512939453125,
          571.789306640625
        ]
      ],
      "group_id": null,
      "description": "",
      "difficult": false,
      "shape_type": "rotation",
      "flags": {},
      "attributes": {}
    },
    {
      "direction": 3.137579917907715,
      "label": "ic",
      "points": [
        [
          176.0325927734375,
          55.63356018066406
        ],
        [
          176.11068725585938,
          75.09300231933594
        ],
        [
          204.0106201171875,
          74.98104858398438
        ],
        [
          203.93252563476562,
          55.5216064453125
        ]
      ],
      "group_id": null,
      "description": "",
      "difficult": false,
      "shape_type": "rotation",
      "flags": {},
      "attributes": {}
    },
    {
      "direction": 0.18102549850940708,
      "label": "un",
      "points": [
        [
          217.25638054899565,
          379.17467539454793
        ],
        [
          220.0211690532657,
          364.0689308287289
        ],
        [
          187.55193854280122,
          358.12610585545207
        ],
        [
          184.78715003853117,
          373.2318504212711
        ]
      ],
      "group_id": null,
      "description": "",
      "difficult": false,
      "shape_type": "rotation",
      "flags": {},
      "attributes": {}
    },
    {
      "direction": 0.10931935161352158,
      "label": "ia",
      "points": [
        [
          217.3926544189453,
          227.48294067382812
        ],
        [
          219.20875549316406,
          210.93643188476562
        ],
        [
          192.4328155517578,
          207.99758911132812
        ],
        [
          190.61671447753906,
          224.54409790039062
        ]
      ],
      "group_id": null,
      "description": "",
      "difficult": false,
      "shape_type": "rotation",
      "flags": {},
      "attributes": {}
    },
    {
      "direction": 0.05862739309668541,
      "label": "11",
      "points": [
        [
          103.724853515625,
          328.5983581542969
        ],
        [
          104.37855529785156,
          317.4610290527344
        ],
        [
          87.57200622558594,
          316.4745788574219
        ],
        [
          86.91830444335938,
          327.6119079589844
        ]
      ],
      "group_id": null,
      "description": "",
      "difficult": false,
      "shape_type": "rotation",
      "flags": {},
      "attributes": {}
    },
    {
      "direction": 0.046956535428762436,
      "label": "9",
      "points": [
        [
          98.10907745361328,
          274.6549987792969
        ],
        [
          98.63842010498047,
          263.3901672363281
        ],
        [
          82.0013198852539,
          262.6083679199219
        ],
        [
          81.47197723388672,
          273.8731994628906
        ]
      ],
      "group_id": null,
      "description": "",
      "difficult": false,
      "shape_type": "rotation",
      "flags": {},
      "attributes": {}
    },
    {
      "direction": 0.10906543582677841,
      "label": "25",
      "points": [
        [
          121.4202651977539,
          626.2498168945312
        ],
        [
          122.34325408935547,
          617.8207397460938
        ],
        [
          106.95653533935547,
          616.1359252929688
        ],
        [
          106.0335464477539,
          624.5650024414062
        ]
      ],
      "group_id": null,
      "description": "",
      "difficult": false,
      "shape_type": "rotation",
      "flags": {},
      "attributes": {}
    },
    {
      "direction": 0.058865297585725784,
      "label": "10",
      "points": [
        [
          101.76058959960938,
          302.7517395019531
        ],
        [
          102.44744873046875,
          291.0969543457031
        ],
        [
          83.76451110839844,
          289.9958801269531
        ],
        [
          83.07765197753906,
          301.6506652832031
        ]
      ],
      "group_id": null,
      "description": "",
      "difficult": false,
      "shape_type": "rotation",
      "flags": {},
      "attributes": {}
    },
    {
      "direction": 0.09170357137918472,
      "label": "26",
      "points": [
        [
          122.26461791992188,
          641.5040283203125
        ],
        [
          122.91291809082031,
          634.454345703125
        ],
        [
          107.51986694335938,
          633.038818359375
        ],
        [
          106.87156677246094,
          640.0885009765625
        ]
      ],
      "group_id": null,
      "description": "",
      "difficult": false,
      "shape_type": "rotation",
      "flags": {},
      "attributes": {}
    },
    {
      "direction": 0.05812779814004898,
      "label": "ia'",
      "points": [
        [
          214.01205444335938,
          199.12139892578125
        ],
        [
          215.12924194335938,
          179.9237060546875
        ],
        [
          183.1368408203125,
          178.06195068359375
        ],
        [
          182.0196533203125,
          197.2596435546875
        ]
      ],
      "group_id": null,
      "description": "",
      "difficult": false,
      "shape_type": "rotation",
      "flags": {},
      "attributes": {}
    },
    {
      "direction": 0.10434449464082718,
      "label": "uc",
      "points": [
        [
          214.2926483154297,
          254.9052276611328
        ],
        [
          215.9896697998047,
          238.7006072998047
        ],
        [
          184.5160369873047,
          235.40452575683594
        ],
        [
          182.8190155029297,
          251.60914611816406
        ]
      ],
      "group_id": null,
      "description": "",
      "difficult": false,
      "shape_type": "rotation",
      "flags": {},
      "attributes": {}
    },
    {
      "direction": 0.1210685236752033,
      "label": "ib",
      "points": [
        [
          204.68634686346866,
          304.0590405904059
        ],
        [
          180.61873022383887,
          301.1308892311115
        ],
        [
          182.64864381964358,
          284.4462386646964
        ],
        [
          206.71626045927334,
          287.37439002399077
        ]
      ],
      "group_id": null,
      "description": "",
      "difficult": false,
      "shape_type": "rotation",
      "flags": {},
      "attributes": {}
    },
    {
      "direction": 3.061685085296631,
      "label": "uv",
      "points": [
        [
          181.12986755371094,
          18.016414642333984
        ],
        [
          182.87721252441406,
          39.836795806884766
        ],
        [
          221.0152130126953,
          36.78277587890625
        ],
        [
          219.2678680419922,
          14.962393760681152
        ]
      ],
      "group_id": null,
      "description": "",
      "difficult": false,
      "shape_type": "rotation",
      "flags": {},
      "attributes": {}
    },
    {
      "direction": 0.1078144907951355,
      "label": "23",
      "points": [
        [
          119.51763916015625,
          591.7425537109375
        ],
        [
          120.49111938476562,
          582.7484130859375
        ],
        [
          104.36038208007812,
          581.0025634765625
        ],
        [
          103.38690185546875,
          589.9967041015625
        ]
      ],
      "group_id": null,
      "description": "",
      "difficult": false,
      "shape_type": "rotation",
      "flags": {},
      "attributes": {}
    },
    {
      "direction": 0.09504960477352142,
      "label": "25",
      "points": [
        [
          122.62464904785156,
          641.6538696289062
        ],
        [
          123.30972290039062,
          634.4679565429688
        ],
        [
          107.01693725585938,
          632.9146118164062
        ],
        [
          106.33186340332031,
          640.1005249023438
        ]
      ],
      "group_id": null,
      "description": "",
      "difficult": false,
      "shape_type": "rotation",
      "flags": {},
      "attributes": {}
    },
    {
      "direction": 0.16050061583518982,
      "label": "uxn",
      "points": [
        [
          229.31704751327908,
          359.5149849191363
        ],
        [
          231.8396610386697,
          343.9330757394488
        ],
        [
          188.56204263046658,
          336.9267280831988
        ],
        [
          186.03942910507595,
          352.5086372628863
        ]
      ],
      "group_id": null,
      "description": "",
      "difficult": false,
      "shape_type": "rotation",
      "flags": {},
      "attributes": {}
    },
    {
      "direction": 0.00039510492933914065,
      "label": "iu",
      "points": [
        [
          221.13451911954422,
          101.96430693341358
        ],
        [
          221.14150764493485,
          84.29000578595262
        ],
        [
          189.76284553555985,
          84.2776003904448
        ],
        [
          189.75585701016922,
          101.95190153790577
        ]
      ],
      "group_id": null,
      "description": "",
      "difficult": false,
      "shape_type": "rotation",
      "flags": {},
      "attributes": {}
    },
    {
      "direction": 0.00039510492933914065,
      "label": "iu",
      "points": [
        [
          221.13451911954422,
          101.96430693341358
        ],
        [
          221.14150764493485,
          84.29000578595262
        ],
        [
          189.76284553555985,
          84.2776003904448
        ],
        [
          189.75585701016922,
          101.95190153790577
        ]
      ],
      "group_id": null,
      "description": "",
      "difficult": false,
      "shape_type": "rotation",
      "flags": {},
      "attributes": {}
    },
    {
      "direction": 0.05039510492933916,
      "label": "uu",
      "points": [
        [
          212.06642066420665,
          138.37638376383765
        ],
        [
          177.50889174848012,
          136.63337766668658
        ],
        [
          178.49780596303034,
          117.02677295064396
        ],
        [
          213.0553348787569,
          118.76977904779503
        ]
      ],
      "group_id": null,
      "description": "",
      "difficult": false,
      "shape_type": "rotation",
      "flags": {},
      "attributes": {}
    },
    {
      "direction": 0.08039510492933916,
      "label": "3io",
      "points": [
        [
          230.8856088560886,
          173.06273062730628
        ],
        [
          192.11903298552184,
          169.93935561196858
        ],
        [
          193.95470575413285,
          147.15542883134248
        ],
        [
          232.7212816246996,
          150.27880384668015
        ]
      ],
      "group_id": null,
      "description": "",
      "difficult": false,
      "shape_type": "rotation",
      "flags": {},
      "attributes": {}
    },
    {
      "direction": 0.16106852367520333,
      "label": "iw'",
      "points": [
        [
          213.50766970904286,
          330.83127905691
        ],
        [
          182.70673289687093,
          325.8268659911144
        ],
        [
          185.26643536521325,
          310.07252418343217
        ],
        [
          216.06737217738518,
          315.0769372492276
        ]
      ],
      "group_id": null,
      "description": "",
      "difficult": false,
      "shape_type": "rotation",
      "flags": {},
      "attributes": {}
    }
  ],
  "imagePath": "IMG_20251106_114551.jpg",
  "imageData": null,
  "imageHeight": 640,
  "imageWidth": 640,
  "text": ""
}