{
  "version": "2.3.6",
  "flags": {},
  "shapes": [
    {
      "direction": 1.719999999999985,
      "label": "uw",
      "points": [
        [
          194.69199464439302,
          461.26023513895643
        ],
        [
          179.76926364081004,
          560.5327978873784
        ],
        [
          144.0795015903619,
          555.1678843209742
        ],
        [
          159.00223259394494,
          455.89532157255223
        ]
      ],
      "group_id": null,
      "description": "",
      "difficult": false,
      "shape_type": "rotation",
      "flags": {},
      "attributes": {}
    }
  ],
  "imagePath": "..\\images\\IMG_20251023_095744.jpg",
  "imageData": null,
  "imageHeight": 640,
  "imageWidth": 640
}