{
  "version": "2.3.6",
  "flags": {},
  "shapes": [
    {
      "direction": 0.08381710946559906,
      "label": "ib",
      "points": [
        [
          221.13809204101562,
          510.94610595703125
        ],
        [
          222.96267700195312,
          489.22833251953125
        ],
        [
          187.02639770507812,
          486.20916748046875
        ],
        [
          185.20181274414062,
          507.92694091796875
        ]
      ],
      "group_id": null,
      "description": "",
      "difficult": false,
      "shape_type": "rotation",
      "flags": {},
      "attributes": {}
    },
    {
      "direction": 0.06770282238721848,
      "label": "ia'",
      "points": [
        [
          227.78643798828125,
          479.0098571777344
        ],
        [
          229.3211669921875,
          456.3760070800781
        ],
        [
          192.12509155273438,
          453.8538513183594
        ],
        [
          190.59036254882812,
          476.4877014160156
        ]
      ],
      "group_id": null,
      "description": "",
      "difficult": false,
      "shape_type": "rotation",
      "flags": {},
      "attributes": {}
    },
    {
      "direction": 0.015742965042591095,
      "label": "1",
      "points": [
        [
          114.61834618596743,
          58.03825378417969
        ],
        [
          114.79801842717836,
          46.62602233886719
        ],
        [
          97.56660363225649,
          46.35472869873047
        ],
        [
          97.38693139104555,
          57.76696014404297
        ]
      ],
      "group_id": null,
      "description": "",
      "difficult": false,
      "shape_type": "rotation",
      "flags": {},
      "attributes": {}
    },
    {
      "direction": 0.030321212485432625,
      "label": "11",
      "points": [
        [
          100.7798080444336,
          383.2626647949219
        ],
        [
          101.21477508544922,
          368.9218444824219
        ],
        [
          78.94725799560547,
          368.2464294433594
        ],
        [
          78.51229095458984,
          382.5872497558594
        ]
      ],
      "group_id": null,
      "description": "",
      "difficult": false,
      "shape_type": "rotation",
      "flags": {},
      "attributes": {}
    },
    {
      "direction": 0.023373734205961227,
      "label": "5",
      "points": [
        [
          107.70142364501953,
          189.11184692382812
        ],
        [
          108.01151275634766,
          175.84750366210938
        ],
        [
          88.5698013305664,
          175.39300537109375
        ],
        [
          88.25971221923828,
          188.6573486328125
        ]
      ],
      "group_id": null,
      "description": "",
      "difficult": false,
      "shape_type": "rotation",
      "flags": {},
      "attributes": {}
    },
    {
      "direction": 0.014804731123149395,
      "label": "2",
      "points": [
        [
          112.81356811523438,
          90.24082946777344
        ],
        [
          112.98973083496094,
          78.34312438964844
        ],
        [
          95.15673828125,
          78.07908630371094
        ],
        [
          94.98057556152344,
          89.97679138183594
        ]
      ],
      "group_id": null,
      "description": "",
      "difficult": false,
      "shape_type": "rotation",
      "flags": {},
      "attributes": {}
    },
    {
      "direction": 0.01309829019010067,
      "label": "13",
      "points": [
        [
          97.33898162841797,
          450.73626708984375
        ],
        [
          97.52938079833984,
          436.200439453125
        ],
        [
          74.55110931396484,
          435.89947509765625
        ],
        [
          74.36071014404297,
          450.435302734375
        ]
      ],
      "group_id": null,
      "description": "",
      "difficult": false,
      "shape_type": "rotation",
      "flags": {},
      "attributes": {}
    },
    {
      "direction": 0.01944262720644474,
      "label": "12",
      "points": [
        [
          99.19779205322266,
          417.36279296875
        ],
        [
          99.4719467163086,
          403.26422119140625
        ],
        [
          76.9666519165039,
          402.82659912109375
        ],
        [
          76.69249725341797,
          416.9251708984375
        ]
      ],
      "group_id": null,
      "description": "",
      "difficult": false,
      "shape_type": "rotation",
      "flags": {},
      "attributes": {}
    },
    {
      "direction": 0.012928638607263565,
      "label": "7",
      "points": [
        [
          104.41751861572266,
          251.7975311279297
        ],
        [
          104.58795928955078,
          238.61558532714844
        ],
        [
          85.3235855102539,
          238.3665008544922
        ],
        [
          85.15314483642578,
          251.54844665527344
        ]
      ],
      "group_id": null,
      "description": "",
      "difficult": false,
      "shape_type": "rotation",
      "flags": {},
      "attributes": {}
    },
    {
      "direction": 0.026509294286370277,
      "label": "18",
      "points": [
        [
          89.71279907226562,
          615.9833374023438
        ],
        [
          90.08944702148438,
          601.7787475585938
        ],
        [
          67.8299560546875,
          601.1885375976562
        ],
        [
          67.45330810546875,
          615.3931274414062
        ]
      ],
      "group_id": null,
      "description": "",
      "difficult": false,
      "shape_type": "rotation",
      "flags": {},
      "attributes": {}
    },
    {
      "direction": 0.023611638695001602,
      "label": "17",
      "points": [
        [
          89.71800231933594,
          583.5863037109375
        ],
        [
          90.05964660644531,
          569.11962890625
        ],
        [
          68.0880126953125,
          568.6007080078125
        ],
        [
          67.74636840820312,
          583.0673828125
        ]
      ],
      "group_id": null,
      "description": "",
      "difficult": false,
      "shape_type": "rotation",
      "flags": {},
      "attributes": {}
    },
    {
      "direction": 0.013183490373194218,
      "label": "8",
      "points": [
        [
          103.5427017211914,
          283.8912353515625
        ],
        [
          103.71732330322266,
          270.64678955078125
        ],
        [
          83.2135238647461,
          270.37646484375
        ],
        [
          83.03890228271484,
          283.62091064453125
        ]
      ],
      "group_id": null,
      "description": "",
      "difficult": false,
      "shape_type": "rotation",
      "flags": {},
      "attributes": {}
    },
    {
      "direction": 0.028694448992609978,
      "label": "4",
      "points": [
        [
          108.82215881347656,
          157.853271484375
        ],
        [
          109.19618225097656,
          144.82208251953125
        ],
        [
          90.70169067382812,
          144.291259765625
        ],
        [
          90.32766723632812,
          157.32244873046875
        ]
      ],
      "group_id": null,
      "description": "",
      "difficult": false,
      "shape_type": "rotation",
      "flags": {},
      "attributes": {}
    },
    {
      "direction": 0.03268809616565704,
      "label": "16",
      "points": [
        [
          91.65219116210938,
          551.3026733398438
        ],
        [
          92.12379455566406,
          536.8805541992188
        ],
        [
          70.43763732910156,
          536.1714477539062
        ],
        [
          69.96603393554688,
          550.5935668945312
        ]
      ],
      "group_id": null,
      "description": "",
      "difficult": false,
      "shape_type": "rotation",
      "flags": {},
      "attributes": {}
    },
    {
      "direction": 0.020384136587381363,
      "label": "3",
      "points": [
        [
          110.4256362915039,
          124.817138671875
        ],
        [
          110.6797103881836,
          112.35491943359375
        ],
        [
          92.06693267822266,
          111.9754638671875
        ],
        [
          91.81285858154297,
          124.43768310546875
        ]
      ],
      "group_id": null,
      "description": "",
      "difficult": false,
      "shape_type": "rotation",
      "flags": {},
      "attributes": {}
    },
    {
      "direction": 0.019127197563648224,
      "label": "6",
      "points": [
        [
          105.96918487548828,
          220.52989196777344
        ],
        [
          106.22234344482422,
          207.29637145996094
        ],
        [
          86.53144073486328,
          206.91969299316406
        ],
        [
          86.27828216552734,
          220.15321350097656
        ]
      ],
      "group_id": null,
      "description": "",
      "difficult": false,
      "shape_type": "rotation",
      "flags": {},
      "attributes": {}
    },
    {
      "direction": 0.020362135022878647,
      "label": "14",
      "points": [
        [
          95.86238861083984,
          485.95782470703125
        ],
        [
          96.16812896728516,
          470.94500732421875
        ],
        [
          73.44702911376953,
          470.4822998046875
        ],
        [
          73.14128875732422,
          485.4951171875
        ]
      ],
      "group_id": null,
      "description": "",
      "difficult": false,
      "shape_type": "rotation",
      "flags": {},
      "attributes": {}
    },
    {
      "direction": 0.010378900915384293,
      "label": "9",
      "points": [
        [
          102.77410125732422,
          316.16644287109375
        ],
        [
          102.91712188720703,
          302.38641357421875
        ],
        [
          82.41289520263672,
          302.173583984375
        ],
        [
          82.2698745727539,
          315.95361328125
        ]
      ],
      "group_id": null,
      "description": "",
      "difficult": false,
      "shape_type": "rotation",
      "flags": {},
      "attributes": {}
    },
    {
      "direction": 0.021164704114198685,
      "label": "10",
      "points": [
        [
          103.12910461425781,
          349.7963562011719
        ],
        [
          103.42930603027344,
          335.6147766113281
        ],
        [
          80.68690490722656,
          335.1333923339844
        ],
        [
          80.38670349121094,
          349.3149719238281
        ]
      ],
      "group_id": null,
      "description": "",
      "difficult": false,
      "shape_type": "rotation",
      "flags": {},
      "attributes": {}
    },
    {
      "direction": 0.011417221277952194,
      "label": "uxn",
      "points": [
        [
          256.68472368866753,
          239.5654605992166
        ],
        [
          256.9156196847613,
          219.34191933945098
        ],
        [
          201.43731768280816,
          218.70849648788848
        ],
        [
          201.2064216867144,
          238.9320377476541
        ]
      ],
      "group_id": null,
      "description": "",
      "difficult": false,
      "shape_type": "rotation",
      "flags": {},
      "attributes": {}
    },
    {
      "direction": 0.019497772678732872,
      "label": "15",
      "points": [
        [
          94.27204895019531,
          518.7348022460938
        ],
        [
          94.55641174316406,
          504.1519775390625
        ],
        [
          72.11747741699219,
          503.71441650390625
        ],
        [
          71.83311462402344,
          518.2972412109375
        ]
      ],
      "group_id": null,
      "description": "",
      "difficult": false,
      "shape_type": "rotation",
      "flags": {},
      "attributes": {}
    },
    {
      "direction": 0.06841906905174255,
      "label": "ia",
      "points": [
        [
          235.5672149658203,
          445.4230041503906
        ],
        [
          236.9300079345703,
          425.5357971191406
        ],
        [
          202.16038513183594,
          423.1531677246094
        ],
        [
          200.79759216308594,
          443.0403747558594
        ]
      ],
      "group_id": null,
      "description": "",
      "difficult": false,
      "shape_type": "rotation",
      "flags": {},
      "attributes": {}
    },
    {
      "direction": 3.137913942337036,
      "label": "uc",
      "points": [
        [
          203.26581007616107,
          125.28826904296875
        ],
        [
          241.15547716119843,
          125.1488832695339
        ],
        [
          241.21771217712177,
          142.06642066420665
        ],
        [
          203.32804509208447,
          142.2058064376415
        ]
      ],
      "group_id": null,
      "description": "",
      "difficult": false,
      "shape_type": "rotation",
      "flags": {},
      "attributes": {}
    },
    {
      "direction": 3.0917649269104004,
      "label": "un3",
      "points": [
        [
          358.78314208984375,
          151.27821350097656
        ],
        [
          359.7015380859375,
          169.69447326660156
        ],
        [
          423.7198486328125,
          166.50193786621094
        ],
        [
          422.80145263671875,
          148.08567810058594
        ]
      ],
      "group_id": null,
      "description": "",
      "difficult": false,
      "shape_type": "rotation",
      "flags": {},
      "attributes": {}
    },
    {
      "direction": 3.117246150970459,
      "label": "uw",
      "points": [
        [
          364.07237361893885,
          123.8099365234375
        ],
        [
          364.6086895369076,
          145.83328247070312
        ],
        [
          421.3112041853451,
          144.4525146484375
        ],
        [
          420.77488826737635,
          122.42916870117188
        ]
      ],
      "group_id": null,
      "description": "",
      "difficult": false,
      "shape_type": "rotation",
      "flags": {},
      "attributes": {}
    },
    {
      "direction": 3.1261799335479736,
      "label": "ux",
      "points": [
        [
          200.47726440429688,
          189.03623962402344
        ],
        [
          200.80032348632812,
          209.9948272705078
        ],
        [
          245.80050659179688,
          209.3011932373047
        ],
        [
          245.47744750976562,
          188.3426055908203
        ]
      ],
      "group_id": null,
      "description": "",
      "difficult": false,
      "shape_type": "rotation",
      "flags": {},
      "attributes": {}
    },
    {
      "direction": 3.1344242668151843,
      "label": "ua",
      "points": [
        [
          205.7250968065626,
          65.60742556897746
        ],
        [
          205.86154523575428,
          84.63989173701576
        ],
        [
          246.2180223558176,
          84.3505975023116
        ],
        [
          246.0815739266259,
          65.3181313342733
        ]
      ],
      "group_id": null,
      "description": "",
      "difficult": false,
      "shape_type": "rotation",
      "flags": {},
      "attributes": {}
    },
    {
      "direction": 3.114864139556884,
      "label": "ub",
      "points": [
        [
          206.05286284625566,
          93.44198979500109
        ],
        [
          206.5796575291054,
          113.14684882660144
        ],
        [
          245.83021101716082,
          112.09748982892569
        ],
        [
          245.30341621988734,
          92.39263461030612
        ]
      ],
      "group_id": null,
      "description": "",
      "difficult": false,
      "shape_type": "rotation",
      "flags": {},
      "attributes": {}
    },
    {
      "direction": 3.1251206588745113,
      "label": "uv",
      "points": [
        [
          351.6591561360558,
          87.02803222263617
        ],
        [
          399.09761673471974,
          86.24655547059609
        ],
        [
          399.48215414975783,
          109.58936504794416
        ],
        [
          352.0436935510939,
          110.37084179998423
        ]
      ],
      "group_id": null,
      "description": "",
      "difficult": false,
      "shape_type": "rotation",
      "flags": {},
      "attributes": {}
    },
    {
      "direction": 3.1285037994384766,
      "label": "un",
      "points": [
        [
          201.9384307861328,
          157.4229736328125
        ],
        [
          202.18055725097656,
          175.91989135742188
        ],
        [
          246.11293029785156,
          175.3448486328125
        ],
        [
          245.8708038330078,
          156.84793090820312
        ]
      ],
      "group_id": null,
      "description": "",
      "difficult": false,
      "shape_type": "rotation",
      "flags": {},
      "attributes": {}
    },
    {
      "direction": 0.07785318046808243,
      "label": "ib'",
      "points": [
        [
          220.91954040527344,
          543.145263671875
        ],
        [
          222.79808044433594,
          519.0648193359375
        ],
        [
          184.6792449951172,
          516.0911865234375
        ],
        [
          182.8007049560547,
          540.171630859375
        ]
      ],
      "group_id": null,
      "description": "",
      "difficult": false,
      "shape_type": "rotation",
      "flags": {},
      "attributes": {}
    },
    {
      "direction": 3.045120658874513,
      "label": "uu",
      "points": [
        [
          356.27968568294403,
          54.321525885868056
        ],
        [
          401.67311095881666,
          49.9286953408053
        ],
        [
          403.6633663366336,
          70.49504950495049
        ],
        [
          358.2699410607609,
          74.88788005001324
        ]
      ],
      "group_id": null,
      "description": "",
      "difficult": false,
      "shape_type": "rotation",
      "flags": {},
      "attributes": {}
    }
  ],
  "imagePath": "IMG_20251106_132434.jpg",
  "imageData": null,
  "imageHeight": 640,
  "imageWidth": 640,
  "text": ""
}